odoo/addons/l10n_es_aeat_sii_force_type/README.rst
odoo/addons/l10n_es_aeat_sii_force_type/__init__.py
odoo/addons/l10n_es_aeat_sii_force_type/__manifest__.py
odoo/addons/l10n_es_aeat_sii_force_type/i18n/es.po
odoo/addons/l10n_es_aeat_sii_force_type/i18n/l10n_es_aeat_sii_force_type.pot
odoo/addons/l10n_es_aeat_sii_force_type/models/__init__.py
odoo/addons/l10n_es_aeat_sii_force_type/models/account_fiscal_position.py
odoo/addons/l10n_es_aeat_sii_force_type/models/account_move.py
odoo/addons/l10n_es_aeat_sii_force_type/readme/CONFIGURE.rst
odoo/addons/l10n_es_aeat_sii_force_type/readme/CONTRIBUTORS.rst
odoo/addons/l10n_es_aeat_sii_force_type/readme/DESCRIPTION.rst
odoo/addons/l10n_es_aeat_sii_force_type/readme/HISTORY.rst
odoo/addons/l10n_es_aeat_sii_force_type/readme/USAGE.rst
odoo/addons/l10n_es_aeat_sii_force_type/static/description/icon.png
odoo/addons/l10n_es_aeat_sii_force_type/static/description/index.html
odoo/addons/l10n_es_aeat_sii_force_type/tests/__init__.py
odoo/addons/l10n_es_aeat_sii_force_type/tests/test_l10n_es_aeat_sii_force_type.py
odoo/addons/l10n_es_aeat_sii_force_type/views/account_fiscal_position_view.xml
odoo/addons/l10n_es_aeat_sii_force_type/views/account_move_view.xml
odoo_addon_l10n_es_aeat_sii_force_type-16.0.2.0.1.dist-info/METADATA
odoo_addon_l10n_es_aeat_sii_force_type-16.0.2.0.1.dist-info/WHEEL
odoo_addon_l10n_es_aeat_sii_force_type-16.0.2.0.1.dist-info/top_level.txt
odoo_addon_l10n_es_aeat_sii_force_type-16.0.2.0.1.dist-info/RECORD
