Metadata-Version: 2.1
Name: odoo-addon-l10n_es_aeat_sii_force_type
Version: 16.0.2.0.1
Summary: Force SII communication type on invoices
Home-page: https://github.com/OCA/l10n-spain
Author: FactorLibre, Odoo Community Association (OCA)
Author-email: support@odoo-community.org
License: AGPL-3
Classifier: Programming Language :: Python
Classifier: Framework :: Odoo
Classifier: Framework :: Odoo :: 16.0
Classifier: License :: OSI Approved :: GNU Affero General Public License v3
Requires-Python: >=3.10
Requires-Dist: odoo-addon-l10n-es-aeat-sii-oca<16.1dev,>=16.0dev
Requires-Dist: odoo<16.1dev,>=16.0a
